passagemath_sws2rst-10.6.43.data/scripts/sage-sws2rst
sage_sws2rst/__init__.py
sage_sws2rst/comments2rst.py
sage_sws2rst/results2rst.py
sage_sws2rst/worksheet2rst.py
passagemath_sws2rst-10.6.43.dist-info/METADATA
passagemath_sws2rst-10.6.43.dist-info/WHEEL
passagemath_sws2rst-10.6.43.dist-info/top_level.txt
passagemath_sws2rst-10.6.43.dist-info/RECORD
