Metadata-Version: 2.4
Name: passagemath-sws2rst
Version: 10.6.43
Summary: passagemath: SageNB worksheet converter
Author-email: The Sage Developers <sage-support@googlegroups.com>
License: GNU General Public License (GPL) v3 or later
Project-URL: Homepage, https://www.sagemath.org
